<?xml version="1.0" encoding="utf-8"?>
<ArrayOfLink xmlns:xsi="http://www.w3.org/2001/XMLSchema-instance" xmlns:xsd="http://www.w3.org/2001/XMLSchema">
  <Link>
    <IdLink>2289</IdLink>
    <IdAssignment>1</IdAssignment>
    <IdPAssignment>2</IdPAssignment>
  </Link>
  <Link>
    <IdLink>2290</IdLink>
    <IdAssignment>2</IdAssignment>
    <IdPAssignment>3</IdPAssignment>
  </Link>
  <Link>
    <IdLink>2291</IdLink>
    <IdAssignment>3</IdAssignment>
    <IdPAssignment>4</IdPAssignment>
  </Link>
  <Link>
    <IdLink>2292</IdLink>
    <IdAssignment>4</IdAssignment>
    <IdPAssignment>5</IdPAssignment>
  </Link>
  <Link>
    <IdLink>2293</IdLink>
    <IdAssignment>4</IdAssignment>
    <IdPAssignment>6</IdPAssignment>
  </Link>
  <Link>
    <IdLink>2294</IdLink>
    <IdAssignment>5</IdAssignment>
    <IdPAssignment>7</IdPAssignment>
  </Link>
  <Link>
    <IdLink>2295</IdLink>
    <IdAssignment>5</IdAssignment>
    <IdPAssignment>8</IdPAssignment>
  </Link>
  <Link>
    <IdLink>2296</IdLink>
    <IdAssignment>6</IdAssignment>
    <IdPAssignment>7</IdPAssignment>
  </Link>
  <Link>
    <IdLink>2297</IdLink>
    <IdAssignment>6</IdAssignment>
    <IdPAssignment>8</IdPAssignment>
  </Link>
  <Link>
    <IdLink>2298</IdLink>
    <IdAssignment>7</IdAssignment>
    <IdPAssignment>9</IdPAssignment>
  </Link>
  <Link>
    <IdLink>2299</IdLink>
    <IdAssignment>7</IdAssignment>
    <IdPAssignment>10</IdPAssignment>
  </Link>
  <Link>
    <IdLink>2300</IdLink>
    <IdAssignment>7</IdAssignment>
    <IdPAssignment>11</IdPAssignment>
  </Link>
  <Link>
    <IdLink>2301</IdLink>
    <IdAssignment>7</IdAssignment>
    <IdPAssignment>12</IdPAssignment>
  </Link>
  <Link>
    <IdLink>2302</IdLink>
    <IdAssignment>7</IdAssignment>
    <IdPAssignment>13</IdPAssignment>
  </Link>
  <Link>
    <IdLink>2303</IdLink>
    <IdAssignment>7</IdAssignment>
    <IdPAssignment>14</IdPAssignment>
  </Link>
  <Link>
    <IdLink>2304</IdLink>
    <IdAssignment>8</IdAssignment>
    <IdPAssignment>9</IdPAssignment>
  </Link>
  <Link>
    <IdLink>2305</IdLink>
    <IdAssignment>8</IdAssignment>
    <IdPAssignment>10</IdPAssignment>
  </Link>
  <Link>
    <IdLink>2306</IdLink>
    <IdAssignment>8</IdAssignment>
    <IdPAssignment>11</IdPAssignment>
  </Link>
  <Link>
    <IdLink>2307</IdLink>
    <IdAssignment>8</IdAssignment>
    <IdPAssignment>12</IdPAssignment>
  </Link>
  <Link>
    <IdLink>2308</IdLink>
    <IdAssignment>8</IdAssignment>
    <IdPAssignment>13</IdPAssignment>
  </Link>
  <Link>
    <IdLink>2309</IdLink>
    <IdAssignment>8</IdAssignment>
    <IdPAssignment>14</IdPAssignment>
  </Link>
  <Link>
    <IdLink>2310</IdLink>
    <IdAssignment>9</IdAssignment>
    <IdPAssignment>15</IdPAssignment>
  </Link>
  <Link>
    <IdLink>2311</IdLink>
    <IdAssignment>9</IdAssignment>
    <IdPAssignment>17</IdPAssignment>
  </Link>
  <Link>
    <IdLink>2312</IdLink>
    <IdAssignment>10</IdAssignment>
    <IdPAssignment>15</IdPAssignment>
  </Link>
  <Link>
    <IdLink>2313</IdLink>
    <IdAssignment>10</IdAssignment>
    <IdPAssignment>17</IdPAssignment>
  </Link>
  <Link>
    <IdLink>2314</IdLink>
    <IdAssignment>11</IdAssignment>
    <IdPAssignment>15</IdPAssignment>
  </Link>
  <Link>
    <IdLink>2315</IdLink>
    <IdAssignment>11</IdAssignment>
    <IdPAssignment>17</IdPAssignment>
  </Link>
  <Link>
    <IdLink>2316</IdLink>
    <IdAssignment>12</IdAssignment>
    <IdPAssignment>15</IdPAssignment>
  </Link>
  <Link>
    <IdLink>2317</IdLink>
    <IdAssignment>12</IdAssignment>
    <IdPAssignment>17</IdPAssignment>
  </Link>
  <Link>
    <IdLink>2318</IdLink>
    <IdAssignment>13</IdAssignment>
    <IdPAssignment>15</IdPAssignment>
  </Link>
  <Link>
    <IdLink>2319</IdLink>
    <IdAssignment>13</IdAssignment>
    <IdPAssignment>17</IdPAssignment>
  </Link>
  <Link>
    <IdLink>2320</IdLink>
    <IdAssignment>14</IdAssignment>
    <IdPAssignment>15</IdPAssignment>
  </Link>
  <Link>
    <IdLink>2321</IdLink>
    <IdAssignment>14</IdAssignment>
    <IdPAssignment>17</IdPAssignment>
  </Link>
  <Link>
    <IdLink>2322</IdLink>
    <IdAssignment>15</IdAssignment>
    <IdPAssignment>16</IdPAssignment>
  </Link>
  <Link>
    <IdLink>2323</IdLink>
    <IdAssignment>17</IdAssignment>
    <IdPAssignment>18</IdPAssignment>
  </Link>
  <Link>
    <IdLink>2324</IdLink>
    <IdAssignment>18</IdAssignment>
    <IdPAssignment>19</IdPAssignment>
  </Link>
  <Link>
    <IdLink>2325</IdLink>
    <IdAssignment>19</IdAssignment>
    <IdPAssignment>20</IdPAssignment>
  </Link>
  <Link>
    <IdLink>2326</IdLink>
    <IdAssignment>20</IdAssignment>
    <IdPAssignment>21</IdPAssignment>
  </Link>
  <Link>
    <IdLink>2327</IdLink>
    <IdAssignment>21</IdAssignment>
    <IdPAssignment>22</IdPAssignment>
  </Link>
  <Link>
    <IdLink>2328</IdLink>
    <IdAssignment>22</IdAssignment>
    <IdPAssignment>23</IdPAssignment>
  </Link>
  <Link>
    <IdLink>2329</IdLink>
    <IdAssignment>16</IdAssignment>
    <IdPAssignment>21</IdPAssignment>
  </Link>
</ArrayOfLink>